pimht/__init__.py
pimht/pimht.py
pimht/util.py
pimht-0.4.6.dist-info/licenses/LICENSE
pimht-0.4.6.dist-info/METADATA
pimht-0.4.6.dist-info/WHEEL
pimht-0.4.6.dist-info/top_level.txt
pimht-0.4.6.dist-info/RECORD
