Metadata-Version: 2.4
Name: pimht
Version: 0.4.6
Summary: Parser for mhtml files
Home-page: https://github.com/pilate/pimht
License: MIT License
License-File: LICENSE
Requires-Dist: chardet
Provides-Extra: speedups
Requires-Dist: faust-cchardet; extra == "speedups"
Requires-Dist: pybase64; extra == "speedups"
Dynamic: license-file
